teamtomo_basemodel/__init__.py
teamtomo_basemodel/custom_models.py
teamtomo_basemodel/custom_types.py
teamtomo_basemodel-0.1.1.dist-info/METADATA
teamtomo_basemodel-0.1.1.dist-info/WHEEL
teamtomo_basemodel-0.1.1.dist-info/licenses/LICENSE
teamtomo_basemodel-0.1.1.dist-info/RECORD
